thunor/__init__.py
thunor/_version.py
thunor/config.py
thunor/curve_fit.py
thunor/dip.py
thunor/helpers.py
thunor/io.py
thunor/plots.py
thunor/viability.py
thunor/converters/__init__.py
thunor/converters/ctrp2.py
thunor/converters/gdsc.py
thunor/converters/teicher.py
thunor/tests/__init__.py
thunor/tests/test_curve_fit.py
thunor/tests/test_dip.py
thunor/tests/test_io.py
thunor/tests/test_plots.py
thunor-0.3.0.dist-info/LICENSE
thunor-0.3.0.dist-info/METADATA
thunor-0.3.0.dist-info/WHEEL
thunor-0.3.0.dist-info/top_level.txt
thunor-0.3.0.dist-info/RECORD
