Metadata-Version: 2.1
Name: thunor
Version: 0.3.0
Summary: Dose response curve and drug induced proliferation (DIP) rate fits and visualisation
Author-email: Alex Lubbock <code@alexlubbock.com>
License: GPL-3.0-only
Project-URL: Homepage, https://www.thunor.net
Classifier: Intended Audience :: Science/Research
Classifier: Programming Language :: Python
Classifier: Topic :: Scientific/Engineering :: Bio-Informatics
Classifier: Topic :: Scientific/Engineering :: Chemistry
Classifier: Topic :: Scientific/Engineering :: Medical Science Apps.
Requires-Python: >=3.10
License-File: LICENSE
Requires-Dist: numpy
Requires-Dist: scipy
Requires-Dist: pandas
Requires-Dist: plotly
Requires-Dist: seaborn
Requires-Dist: tables
Provides-Extra: docs
Requires-Dist: sphinx ; extra == 'docs'
Requires-Dist: sphinx-rtd-theme ; extra == 'docs'
Requires-Dist: mock ; extra == 'docs'
Requires-Dist: nbsphinx ; extra == 'docs'
Requires-Dist: ipykernel ; extra == 'docs'
Provides-Extra: test
Requires-Dist: pytest ; extra == 'test'
Requires-Dist: nbval ; extra == 'test'
Requires-Dist: django ; extra == 'test'
Requires-Dist: nbformat ; extra == 'test'
Requires-Dist: flake8 ; extra == 'test'
Requires-Dist: codecov ; extra == 'test'
Requires-Dist: pytest-cov ; extra == 'test'
